{
  "en": [
    "CHIPS",
    "SWIFT",
    "Fedwire",
    "ACH",
    "RTP",
    "SEPA",
    "TARGET2",
    "CIPS",
    "FedNow",
    "BACS",
    "SIC",
    "EBA",
    "CHATS",
    "HKD",
    "ZENGIN",
    "NEFT",
    "IMPS",
    "ACH_US",
    "ACH_CANADA",
    "BECS",
    "PAGO",
    "CADE",
    "SPB",
    "STRIPE",
    "WISE",
    "PAYPAL",
    "REVOLUT",
    "BGP",
    "OSPF",
    "EIGRP",
    "RIP",
    "IS-IS",
    "MPLS",
    "VLAN",
    "SDN",
    "IPv4",
    "IPv6",
    "VPN",
    "VPC",
    "GRE Tunnel",
    "IPsec",
    "Load Balancer",
    "OSPF",
    "BGP",
    "EIGRP",
    "RIP",
    "IS-IS",
    "MPLS",
    "VLAN",
    "VXLAN",
    "STP",
    "RSTP",
    "MSTP",
    "PVST",
    "HSRP",
    "VRRP",
    "GLBP",
    "CARP",
    "ECMP",
    "LACP",
    "BFD",
    "PIM",
    "IGMP",
    "MLD",
    "NDP",
    "DHCP",
    "DNS",
    "ARP",
    "NAT",
    "PAT",
    "ACL",
    "QoS",
    "DiffServ",
    "IntServ",
    "MP-BGP",
    "eBGP",
    "iBGP",
    "IS-IS L1",
    "IS-IS L2",
    "OSPFv3",
    "EIGRPv6",
    "RIPng",
    "PBR",
    "SD-WAN",
    "VPLS",
    "EVPN",
    "Segment Routing",
    "SR-MPLS",
    "SRv6",
    "LISP",
    "OAM",
    "Y.1731",
    "CFM",
    "TWAMP",
    "NetFlow",
    "sFlow",
    "IPFIX",
    "SNMP",
    "NETCONF",
    "RESTCONF"
  ],
  "fr": [
    "CHIPS",
    "SWIFT",
    "Fedwire",
    "ACH",
    "RTP",
    "SEPA",
    "TARGET2",
    "CIPS",
    "FedNow",
    "BACS",
    "SIC",
    "EBA",
    "CHATS",
    "HKD",
    "ZENGIN",
    "NEFT",
    "IMPS",
    "ACH_US",
    "ACH_CANADA",
    "BECS",
    "PAGO",
    "CADE",
    "SPB",
    "STRIPE",
    "WISE",
    "PAYPAL",
    "REVOLUT",
    "BGP",
    "OSPF",
    "EIGRP",
    "RIP",
    "IS-IS",
    "MPLS",
    "VLAN",
    "SDN",
    "IPv4",
    "IPv6",
    "VPN",
    "VPC",
    "Tunnel GRE",
    "IPsec",
    "Équilibreur de charge",
    "OSPF",
    "BGP",
    "EIGRP",
    "RIP",
    "IS-IS",
    "MPLS",
    "VLAN",
    "VXLAN",
    "STP",
    "RSTP",
    "MSTP",
    "PVST",
    "HSRP",
    "VRRP",
    "GLBP",
    "CARP",
    "ECMP",
    "LACP",
    "BFD",
    "PIM",
    "IGMP",
    "MLD",
    "NDP",
    "DHCP",
    "DNS",
    "ARP",
    "NAT",
    "PAT",
    "ACL",
    "QoS",
    "DiffServ",
    "IntServ",
    "MP-BGP",
    "eBGP",
    "iBGP",
    "IS-IS L1",
    "IS-IS L2",
    "OSPFv3",
    "EIGRPv6",
    "RIPng",
    "PBR",
    "SD-WAN",
    "VPLS",
    "EVPN",
    "Segment Routing",
    "SR-MPLS",
    "SRv6",
    "LISP",
    "OAM",
    "Y.1731",
    "CFM",
    "TWAMP",
    "NetFlow",
    "sFlow",
    "IPFIX",
    "SNMP",
    "NETCONF",
    "RESTCONF"
  ],
  "de": [
    "CHIPS",
    "SWIFT",
    "Fedwire",
    "ACH",
    "RTP",
    "SEPA",
    "TARGET2",
    "CIPS",
    "FedNow",
    "BACS",
    "SIC",
    "EBA",
    "CHATS",
    "HKD",
    "ZENGIN",
    "NEFT",
    "IMPS",
    "ACH_US",
    "ACH_CANADA",
    "BECS",
    "PAGO",
    "CADE",
    "SPB",
    "STRIPE",
    "WISE",
    "PAYPAL",
    "REVOLUT",
    "BGP",
    "OSPF",
    "EIGRP",
    "RIP",
    "IS-IS",
    "MPLS",
    "VLAN",
    "SDN",
    "IPv4",
    "IPv6",
    "VPN",
    "VPC",
    "GRE-Tunnel",
    "IPsec",
    "Lastverteiler",
    "OSPF",
    "BGP",
    "EIGRP",
    "RIP",
    "IS-IS",
    "MPLS",
    "VLAN",
    "VXLAN",
    "STP",
    "RSTP",
    "MSTP",
    "PVST",
    "HSRP",
    "VRRP",
    "GLBP",
    "CARP",
    "ECMP",
    "LACP",
    "BFD",
    "PIM",
    "IGMP",
    "MLD",
    "NDP",
    "DHCP",
    "DNS",
    "ARP",
    "NAT",
    "PAT",
    "ACL",
    "QoS",
    "DiffServ",
    "IntServ",
    "MP-BGP",
    "eBGP",
    "iBGP",
    "IS-IS L1",
    "IS-IS L2",
    "OSPFv3",
    "EIGRPv6",
    "RIPng",
    "PBR",
    "SD-WAN",
    "VPLS",
    "EVPN",
    "Segment Routing",
    "SR-MPLS",
    "SRv6",
    "LISP",
    "OAM",
    "Y.1731",
    "CFM",
    "TWAMP",
    "NetFlow",
    "sFlow",
    "IPFIX",
    "SNMP",
    "NETCONF",
    "RESTCONF"
  ],
  "es": [
    "CHIPS",
    "SWIFT",
    "Fedwire",
    "ACH",
    "RTP",
    "SEPA",
    "TARGET2",
    "CIPS",
    "FedNow",
    "BACS",
    "SIC",
    "EBA",
    "CHATS",
    "HKD",
    "ZENGIN",
    "NEFT",
    "IMPS",
    "ACH_US",
    "ACH_CANADA",
    "BECS",
    "PAGO",
    "CADE",
    "SPB",
    "STRIPE",
    "WISE",
    "PAYPAL",
    "REVOLUT",
    "BGP",
    "OSPF",
    "EIGRP",
    "RIP",
    "IS-IS",
    "MPLS",
    "VLAN",
    "SDN",
    "IPv4",
    "IPv6",
    "VPN",
    "VPC",
    "Túnel GRE",
    "IPsec",
    "Balanceador de carga",
    "OSPF",
    "BGP",
    "EIGRP",
    "RIP",
    "IS-IS",
    "MPLS",
    "VLAN",
    "VXLAN",
    "STP",
    "RSTP",
    "MSTP",
    "PVST",
    "HSRP",
    "VRRP",
    "GLBP",
    "CARP",
    "ECMP",
    "LACP",
    "BFD",
    "PIM",
    "IGMP",
    "MLD",
    "NDP",
    "DHCP",
    "DNS",
    "ARP",
    "NAT",
    "PAT",
    "ACL",
    "QoS",
    "DiffServ",
    "IntServ",
    "MP-BGP",
    "eBGP",
    "iBGP",
    "IS-IS L1",
    "IS-IS L2",
    "OSPFv3",
    "EIGRPv6",
    "RIPng",
    "PBR",
    "SD-WAN",
    "VPLS",
    "EVPN",
    "Segment Routing",
    "SR-MPLS",
    "SRv6",
    "LISP",
    "OAM",
    "Y.1731",
    "CFM",
    "TWAMP",
    "NetFlow",
    "sFlow",
    "IPFIX",
    "SNMP",
    "NETCONF",
    "RESTCONF"
  ],
  "it": [
    "CHIPS",
    "SWIFT",
    "Fedwire",
    "ACH",
    "RTP",
    "SEPA",
    "TARGET2",
    "CIPS",
    "FedNow",
    "BACS",
    "SIC",
    "EBA",
    "CHATS",
    "HKD",
    "ZENGIN",
    "NEFT",
    "IMPS",
    "ACH_US",
    "ACH_CANADA",
    "BECS",
    "PAGO",
    "CADE",
    "SPB",
    "STRIPE",
    "WISE",
    "PAYPAL",
    "REVOLUT",
    "BGP",
    "OSPF",
    "EIGRP",
    "RIP",
    "IS-IS",
    "MPLS",
    "VLAN",
    "SDN",
    "IPv4",
    "IPv6",
    "VPN",
    "VPC",
    "Tunnel GRE",
    "IPsec",
    "Bilanciatore di carico",
    "OSPF",
    "BGP",
    "EIGRP",
    "RIP",
    "IS-IS",
    "MPLS",
    "VLAN",
    "VXLAN",
    "STP",
    "RSTP",
    "MSTP",
    "PVST",
    "HSRP",
    "VRRP",
    "GLBP",
    "CARP",
    "ECMP",
    "LACP",
    "BFD",
    "PIM",
    "IGMP",
    "MLD",
    "NDP",
    "DHCP",
    "DNS",
    "ARP",
    "NAT",
    "PAT",
    "ACL",
    "QoS",
    "DiffServ",
    "IntServ",
    "MP-BGP",
    "eBGP",
    "iBGP",
    "IS-IS L1",
    "IS-IS L2",
    "OSPFv3",
    "EIGRPv6",
    "RIPng",
    "PBR",
    "SD-WAN",
    "VPLS",
    "EVPN",
    "Segment Routing",
    "SR-MPLS",
    "SRv6",
    "LISP",
    "OAM",
    "Y.1731",
    "CFM",
    "TWAMP",
    "NetFlow",
    "sFlow",
    "IPFIX",
    "SNMP",
    "NETCONF",
    "RESTCONF"
  ],
  "pt": [
    "CHIPS",
    "SWIFT",
    "Fedwire",
    "ACH",
    "RTP",
    "SEPA",
    "TARGET2",
    "CIPS",
    "FedNow",
    "BACS",
    "SIC",
    "EBA",
    "CHATS",
    "HKD",
    "ZENGIN",
    "NEFT",
    "IMPS",
    "ACH_US",
    "ACH_CANADA",
    "BECS",
    "PAGO",
    "CADE",
    "SPB",
    "STRIPE",
    "WISE",
    "PAYPAL",
    "REVOLUT",
    "BGP",
    "OSPF",
    "EIGRP",
    "RIP",
    "IS-IS",
    "MPLS",
    "VLAN",
    "SDN",
    "IPv4",
    "IPv6",
    "VPN",
    "VPC",
    "Túnel GRE",
    "IPsec",
    "Balanceador de carga",
    "OSPF",
    "BGP",
    "EIGRP",
    "RIP",
    "IS-IS",
    "MPLS",
    "VLAN",
    "VXLAN",
    "STP",
    "RSTP",
    "MSTP",
    "PVST",
    "HSRP",
    "VRRP",
    "GLBP",
    "CARP",
    "ECMP",
    "LACP",
    "BFD",
    "PIM",
    "IGMP",
    "MLD",
    "NDP",
    "DHCP",
    "DNS",
    "ARP",
    "NAT",
    "PAT",
    "ACL",
    "QoS",
    "DiffServ",
    "IntServ",
    "MP-BGP",
    "eBGP",
    "iBGP",
    "IS-IS L1",
    "IS-IS L2",
    "OSPFv3",
    "EIGRPv6",
    "RIPng",
    "PBR",
    "SD-WAN",
    "VPLS",
    "EVPN",
    "Segment Routing",
    "SR-MPLS",
    "SRv6",
    "LISP",
    "OAM",
    "Y.1731",
    "CFM",
    "TWAMP",
    "NetFlow",
    "sFlow",
    "IPFIX",
    "SNMP",
    "NETCONF",
    "RESTCONF"
  ]
}
