{
  "en": ["Nike","Adidas","Apple","Samsung","Sony","Lululemon","Patagonia","Yeti","Dyson","KitchenAid","Vitamix","Levi's","The North Face","Coleman","Under Armour","Philips","Bosch","Braun","OXO","Hydro Flask","Fjallraven","Herschel","JBL","Bose","Shure","Anker","Belkin","Logitech","Razer","Corsair","Nintendo","Microsoft","Canon","Nikon","Fujifilm","GoPro","DJI","Tesla","Ford","Toyota","Honda","BMW","Mercedes","Audi","Volkswagen","IKEA","West Elm","Crate & Barrel","Pottery Barn","Williams Sonoma","REI","Columbia","Merrell","Timberland","Vans","Converse","New Balance","Coca-Cola","Pepsi","Keurig","Nestle","Starbucks","Dunkin","Blue Bottle","Lavazza","Nature Valley","KIND","RXBAR","Quest","Orgain","Garden of Life","Vega","Owyn","L'Oreal","Estee Lauder","Clinique","Neutrogena","CeraVe","La Roche-Posay","Olay","Kiehl's","LEGO","Hasbro","Mattel","Fisher-Price","Melissa & Doug","Crayola","Ravensburger","Playmobil","Procter & Gamble","Unilever","SC Johnson","Clorox","Seventh Generation","Method","Mrs. Meyers","Dawn","Green Giant","Del Monte","Campbell's","Kraft Heinz","General Mills","Kellogg's","Post","Quaker","Zara","H&M","Uniqlo","Gap","Banana Republic","Old Navy","J.Crew","Ralph Lauren"],
  "fr": ["Carrefour","Decathlon","Auchan","Leroy Merlin","Orange","Societe Generale","BNP Paribas","TotalEnergies","Renault","Peugeot","Danone","Lactalis","LVMH","Hermes","Louis Vuitton","Chanel","Michelin","Air France","SNCF","EDF","Nike","Adidas","Apple","Samsung","Sony","Dyson","Philips","Bosch","L'Oreal","LEGO","Microsoft","IKEA","Coca-Cola","Starbucks","Nestle","Unilever","Procter & Gamble","LEGO","Hasbro","Crayola","BMW","Mercedes","Audi","Volkswagen","Toyota","Honda","Zara","H&M","Lavazza","Ravensburger","Playmobil","Patagonia","The North Face","Columbia","Timberland","Vans","Converse","New Balance","Pepsi","Keurig","Samsung","Canon","Nikon","GoPro","Ford","Tesla"],
  "de": ["Aldi","Lidl","BMW","Mercedes-Benz","Volkswagen","Siemens","Deutsche Bank","SAP","Allianz","Bayer","Adidas","Puma","Bosch","RWE","Lufthansa","Deutsche Telekom","T-Mobile","Nike","Adidas","Apple","Samsung","Sony","Dyson","Philips","Braun","IKEA","Coca-Cola","Starbucks","Nestle","Unilever","Procter & Gamble","LEGO","Hasbro","Crayola","Ravensburger","Playmobil","Toyota","Honda","Ford","Tesla","Zara","H&M","Uniqlo","Lavazza","Patagonia","The North Face","Columbia","Timberland","Vans","Converse","New Balance","Pepsi","Keurig","Samsung","Canon","Nikon","GoPro","L'Oreal","Michelin","Danone","Renault","Peugeot","LVMH","Chanel","Porsche","Audi","Opel","Continental","T-Mobile","Deutsche Post","DHL","Commerzbank","HypoVereinsbank","Kaufland","Edeka","Rewe","Netto","dm-drogerie markt","Rossmann","Miele","Vorwerk","WMF","Zwilling","Henkel","Beiersdorf","Nivea"],
  "es": ["Zara","Mercadona","Inditex","Telefonica","BBVA","Santander","Repsol","Iberdrola","Seat","El Corte Ingles","Mapfre","Ferrovial","ACS","Nike","Adidas","Apple","Samsung","Sony","Dyson","Philips","Bosch","IKEA","Coca-Cola","Starbucks","Nestle","Unilever","Procter & Gamble","LEGO","Hasbro","Crayola","Ravensburger","Playmobil","BMW","Mercedes","Audi","Volkswagen","Toyota","Honda","Ford","Tesla","Lavazza","Patagonia","The North Face","Columbia","Timberland","Vans","Converse","New Balance","Pepsi","Keurig","Samsung","Canon","Nikon","GoPro","L'Oreal","Michelin","Danone","Renault","Peugeot","LVMH","Chanel","H&M","Uniqlo","Gap","Desigual","Mango","Adolfo Dominguez","Loewe","Tous","Punt Roma","Camper","Pronovias","Chupa Chups","Freixenet","Codorniu","Mahou","San Miguel","Estrella Damm","Naturgy","Endesa","Gas Natural","Abertis","OHL","Sacyr","Acciona","FCC","Tecnicas Reunidas","Indra","Amadeus","Prisa","Grupo Planeta","Meliá Hotels","Iberia","Vueling","Renfe"],
  "it": ["Ferrari","Lamborghini","Prada","Gucci","Versace","Armani","Fiat","Eni","Luxottica","Barilla","Parmalat","Campari","Lavazza","Benetton","Generali","Intesa Sanpaolo","UniCredit","Nike","Adidas","Apple","Samsung","Sony","Dyson","Philips","Bosch","IKEA","Coca-Cola","Starbucks","Nestle","Unilever","Procter & Gamble","LEGO","Hasbro","Crayola","Ravensburger","Playmobil","BMW","Mercedes","Audi","Volkswagen","Toyota","Honda","Ford","Tesla","Zara","H&M","Uniqlo","Patagonia","The North Face","Columbia","Timberland","Vans","Converse","New Balance","Pepsi","Keurig","Samsung","Canon","Nikon","GoPro","L'Oreal","Michelin","Danone","Renault","LVMH","Chanel","Maserati","Alfa Romeo","Ducati","Piaggio","Bulgari","Fendi","Valentino","Dolce & Gabbana","Giorgio Armani","Salvatore Ferragamo","Missoni","Roberto Cavalli","Etro","Trussardi","Moncler","Geox","Tod's","Bottega Veneta","Pomellato","Damiani","Technogym","De Longhi","Indesit","Smeg","Moleskine","Panerai","Officine Panerai","Peroni","Moretti","Martini","Aperol","Fernet-Branca","San Pellegrino","Acqua Panna","Granarolo","Galbani","Carraro"],
  "pt": ["Natura","Petrobras","Vale","Itau","Bradesco","AmBev","Embraer","BRF","Gerdau","CSN","Oi","Claro","Vivo","CEMIG","CPFL","Nike","Adidas","Apple","Samsung","Sony","Dyson","Philips","Bosch","IKEA","Coca-Cola","Starbucks","Nestle","Unilever","Procter & Gamble","LEGO","Hasbro","Crayola","Ravensburger","Playmobil","BMW","Mercedes","Audi","Volkswagen","Toyota","Honda","Ford","Tesla","Zara","H&M","Uniqlo","Lavazza","Patagonia","The North Face","Columbia","Timberland","Vans","Converse","New Balance","Pepsi","Keurig","Samsung","Canon","Nikon","GoPro","L'Oreal","Michelin","Danone","Renault","LVMH","Chanel","AmBev","Sadia","Perdigao","Seara","Marfrig","JBS","Copersucar","Raizen","Cosan","Ultrapar","Braskem","Fibria","Suzano","Klabin","Votorantim","Camargo Correa","Andrade Gutierrez","Odebrecht","Queiroz Galvao","Magazine Luiza","Lojas Americanas","Lojas Renner","Marisa","Riachuelo","C&A","Casas Bahia","Ponto Frio","Submarino","Americanas","Mercado Livre","PagSeguro","Stone","Cielo","Rede","Banco do Brasil","Caixa Economica","BNDES","Santander Brasil","Itau","Bradesco","Safra","BTG Pactual","XP Investimentos","Eletrobras","Furnas","Chesf","Eletronorte","Eletrosul","Petrobras","Transpetro","Gaspetro","Liquigas","Ultragaz"]
}